emmett_mcp/__init__.py
emmett_mcp/_compat.py
emmett_mcp/ext.py
emmett_mcp/mcp.py
emmett_mcp/pipes.py
emmett_mcp/proto.py
emmett_mcp/sessions.py
emmett_mcp/tasks.py
emmett_mcp/wrappers.py
emmett_mcp-0.1.0.dist-info/METADATA
emmett_mcp-0.1.0.dist-info/WHEEL
emmett_mcp-0.1.0.dist-info/licenses/LICENSE
emmett_mcp-0.1.0.dist-info/RECORD
